LICENSE
MANIFEST.in
README.md
setup.py
django_imapauth.egg-info/PKG-INFO
django_imapauth.egg-info/SOURCES.txt
django_imapauth.egg-info/dependency_links.txt
django_imapauth.egg-info/top_level.txt
imapauth/__init__.py
imapauth/backends.py
imapauth/settings.py